{"trial_id": "39d91a834482309dbe424c30d489bc1b", "hyperparameters": {"space": [{"class_name": "Int", "config": {"name": "units1", "default": null, "conditions": [], "min_value": 8, "max_value": 512, "step": 8, "sampling": null}}, {"class_name": "Int", "config": {"name": "units2", "default": null, "conditions": [], "min_value": 0, "max_value": 128, "step": 8, "sampling": null}}, {"class_name": "Int", "config": {"name": "units3", "default": null, "conditions": [], "min_value": 0, "max_value": 128, "step": 8, "sampling": null}}], "values": {"units1": 376, "units2": 88, "units3": 48, "tuner/epochs": 17, "tuner/initial_epoch": 6, "tuner/bracket": 3, "tuner/round": 2, "tuner/trial_id": "0f156d00b0a23a9d13e276ce238d07cd"}}, "metrics": {"metrics": {"loss": {"direction": "min", "observations": [{"value": [0.9298895478248597], "step": 0}]}, "accuracy": {"direction": "max", "observations": [{"value": [0.994726300239563], "step": 0}]}, "val_loss": {"direction": "min", "observations": [{"value": [0.6650648713111877], "step": 0}]}, "val_accuracy": {"direction": "max", "observations": [{"value": [0.8224299073219299], "step": 0}]}}}, "score": 0.8224299073219299, "best_step": 0, "status": "COMPLETED"}