{"trial_id": "34fe70dc7c8a413bbc73e86734c49ae4", "hyperparameters": {"space": [{"class_name": "Int", "config": {"name": "units1", "default": null, "conditions": [], "min_value": 8, "max_value": 512, "step": 8, "sampling": null}}, {"class_name": "Int", "config": {"name": "units2", "default": null, "conditions": [], "min_value": 0, "max_value": 128, "step": 8, "sampling": null}}, {"class_name": "Int", "config": {"name": "units3", "default": null, "conditions": [], "min_value": 0, "max_value": 128, "step": 8, "sampling": null}}], "values": {"units1": 352, "units2": 64, "units3": 104, "tuner/epochs": 17, "tuner/initial_epoch": 6, "tuner/bracket": 3, "tuner/round": 2, "tuner/trial_id": "bb00f8d32db201aecdc5addddcb44c86"}}, "metrics": {"metrics": {"loss": {"direction": "min", "observations": [{"value": [1.1481206893920899], "step": 0}]}, "accuracy": {"direction": "max", "observations": [{"value": [0.8553724169731141], "step": 0}]}, "val_loss": {"direction": "min", "observations": [{"value": [0.7881197333335876], "step": 0}]}, "val_accuracy": {"direction": "max", "observations": [{"value": [0.7685365676879883], "step": 0}]}}}, "score": 0.7685365676879883, "best_step": 0, "status": "COMPLETED"}