{"trial_id": "989abe12fcac9cb90034338bf0e298b1", "hyperparameters": {"space": [{"class_name": "Int", "config": {"name": "units1", "default": null, "conditions": [], "min_value": 8, "max_value": 512, "step": 8, "sampling": null}}, {"class_name": "Int", "config": {"name": "units2", "default": null, "conditions": [], "min_value": 0, "max_value": 128, "step": 8, "sampling": null}}, {"class_name": "Int", "config": {"name": "units3", "default": null, "conditions": [], "min_value": 0, "max_value": 128, "step": 8, "sampling": null}}], "values": {"units1": 424, "units2": 120, "units3": 104, "tuner/epochs": 50, "tuner/initial_epoch": 17, "tuner/bracket": 1, "tuner/round": 1, "tuner/trial_id": "a7aa8934536b0c7ca00f740b893974e4"}}, "metrics": {"metrics": {"loss": {"direction": "min", "observations": [{"value": [1.0943023681640625], "step": 0}]}, "accuracy": {"direction": "max", "observations": [{"value": [0.9722067356109619], "step": 0}]}, "val_loss": {"direction": "min", "observations": [{"value": [0.925555682182312], "step": 0}]}, "val_accuracy": {"direction": "max", "observations": [{"value": [0.7306930780410766], "step": 0}]}}}, "score": 0.7306930780410766, "best_step": 0, "status": "COMPLETED"}